{"streicheln": 0, "freiheit": 1, "gesundheit": 2, "liebe": 3, "frieden": 4, "freude": 5, "freund": 6, "himmel": 7, "loyal": 8, "vergnuegen": 9, "diamant": 10, "sanft": 11, "ehrlich": 12, "gluecklich": 13, "diplom": 14, "geschenk": 15, "ehre": 16, "wunder": 17, "sonnenaufgang": 18, "familie": 19, "lachen": 20, "paradies": 21, "ferien": 22, "missbrauch": 23, "absturz": 24, "schmutz": 25, "mord": 26, "krankheit": 27, "tod": 28, "trauer": 29, "vergiften": 30, "stinken": 31, "angriff": 32, "katastrophe": 33, "hass": 34, "verschmutzen": 35, "tragoedie": 36, "scheidung": 37, "gefaengnis": 38, "armut": 39, "haesslich": 40, "krebs": 41, "toeten": 42, "faul": 43, "erbrechen": 44, "qual": 45, "geben": 46, "gro\u00dfzuegigkeit": 47, "gro\u00dfzuegig": 48, "selbstlos": 49, "genuegsam": 50, "gro\u00dfmut": 51, "uneigennuetzig": 52, "sparsam": 53, "proletariat": 54, "industriearbeiter": 55, "nehmen": 56, "gier": 57, "gierig": 58, "egoistisch": 59, "habgierig": 60, "habsucht": 61, "eigennuetzig": 62, "verschwenderisch": 63, "bourgeoisie": 64, "wohlstand": 65, "bankier": 66, "wucher": 67, "kamerad": 68, "ehrlichkeit": 69, "ersichtlich": 70, "aufrichtig": 71, "vertrauenswuerdig": 72, "wahr": 73, "unschuldig": 74, "freundschaftlich": 75, "hell": 76, "zugaenglich": 77, "machtlos": 78, "ohnmacht": 79, "untertan": 80, "illoyal": 81, "spitzel": 82, "verrat": 83, "geheim": 84, "betruegerisch": 85, "hinterlistig": 86, "unwahr": 87, "zweifelhaft": 88, "verbrecher": 89, "bedrohlich": 90, "dunkel": 91, "geheimnis": 92, "einflussreich": 93, "weltmacht": 94, "herrschaft": 95, "verschwoerung": 96, "glaeubige": 97, "geistlich": 98, "engel": 99, "heilig": 100, "fromm": 101, "geheiligt": 102, "goettlich": 103, "ehrwuerdig": 104, "treu": 105, "glaeubig": 106, "religioes": 107, "atheist": 108, "weltlich": 109, "teufel": 110, "irdisch": 111, "atheistisch": 112, "heidnisch": 113, "gottlos": 114, "verflucht": 115, "untreu": 116, "unglaeubig": 117, "irreligioes": 118, "gotteslaesterung": 119, "normal": 120, "ueberlegenheit": 121, "gleichheit": 122, "angenehm": 123, "freundlich": 124, "ehrenwert": 125, "sympathie": 126, "akzeptiert": 127, "besser": 128, "national": 129, "rein": 130, "ueberlegen": 131, "sauber": 132, "ehrenhaft": 133, "seltsam": 134, "unterlegenheit": 135, "ungleichheit": 136, "unangenehm": 137, "boshaft": 138, "schaendlich": 139, "abgelehnt": 140, "schlechter": 141, "fremdlaendisch": 142, "unrein": 143, "unterlegen": 144, "schmutzig": 145, "verseucht": 146, "schaedlich": 147, "niedertraechtig": 148, "bescheiden": 149, "sittlich": 150, "anstaendig": 151, "tugendhaft": 152, "charakterfest": 153, "wuerdig": 154, "moralisch": 155, "gesittet": 156, "gewissenhaft": 157, "vorbildlich": 158, "unbescheiden": 159, "unsittlich": 160, "unanstaendig": 161, "luestern": 162, "korrupt": 163, "unwuerdig": 164, "unmoralisch": 165, "unehrlich": 166, "verdorben": 167, "gewissenlos": 168, "barbarisch": 169, "patriotisch": 170, "germanisch": 171, "vaterlaendisch": 172, "deutschnational": 173, "reichstreu": 174, "vaterlandsliebe": 175, "nationalgesinnt": 176, "nationalstolz": 177, "koenigstreu": 178, "volksgeist": 179, "nationalbewusstsein": 180, "volksbewusstsein": 181, "staatstreu": 182, "nationalgefuehl": 183, "unpatriotisch": 184, "undeutsch": 185, "vaterlandslos": 186, "antideutsch": 187, "dissident": 188, "landesverraeter": 189, "reichsfeindlich": 190, "reichsfeind": 191, "deutschfeindlich": 192, "fremd": 193, "nichtdeutsch": 194, "staatsfeindlich": 195, "heimatlos": 196, "jude": 197, "juedisch": 198, "judentum": 199, "orthodox": 200, "israel": 201, "mosaisch": 202, "israelitisch": 203, "israelit": 204, "rothschild": 205, "talmud": 206, "synagoge": 207, "abraham": 208, "rabbiner": 209, "zionistisch": 210, "christ": 211, "christlich": 212, "christentum": 213, "katholizismus": 214, "katholisch": 215, "evangelisch": 216, "evangelium": 217, "auferstehung": 218, "kirche": 219, "jesus": 220, "taufe": 221, "pfarrer": 222, "bibel": 223, "ostern": 224, "protestant": 225, "protestantisch": 226, "protestantismus": 227, "landeskirche": 228, "lutherisch": 229, "evangelisch-lutherisch": 230, "oberkirchenrat": 231, "katholik": 232, "papst": 233, "jesuiten": 234, "ultramontanismus": 235, "roemisch-katholisch": 236, "zentrumspartei": 237}